<?xml version="1.0" encoding="utf-8" standalone="yes"?>
<DCPlusPlus>
	<Settings>
		<MainFrameOrder type="string">0,1,2,3,4,5,6,7,8,9,10,11,12</MainFrameOrder>
		<MainFrameWidths type="string">150,100,250,75,75,175,100,200,50,50,50,100,75</MainFrameWidths>
		<ConfigVersion type="string">8559</ConfigVersion>
		<MainFrameVisible type="string">1,1,1,1,1,1,1,1,1,1,1,1,1</MainFrameVisible>
		<MainWindowState type="int">1</MainWindowState>
		<MainWindowSizeX type="int">1440</MainWindowSizeX>
		<MainWindowSizeY type="int">760</MainWindowSizeY>
		<MainWindowPosX type="int">443</MainWindowPosX>
		<MainWindowPosY type="int">288</MainWindowPosY>
		<CzertHiddenSettingA type="int">0</CzertHiddenSettingA>
		<CzertHiddenSettingB type="int">0</CzertHiddenSettingB>
		<TransferSplitSize type="int">8000</TransferSplitSize>
		<Away type="int">0</Away>
		<ShowWinampControl type="int">0</ShowWinampControl>
		<CustomMenuPath	type="string">http://internet.m2c.ru/files/Hub/custom_menu.xml</CustomMenuPath>	
		<UseCustomMenu type="int">1</UseCustomMenu>
	</Settings>
	<Share/>
	<NoShare/>
	<PreviewApps/>
	<Rebars>
		<Rebar Name="MainToolBar" ID="60160,60161,60162,60163" CX="261,752,200,296" BreakLine="0,1,0,1" BandCount="4"/>
	</Rebars>
	<Rss/>
	<SearchHistory/>
</DCPlusPlus>
